{"title":"Создано в @sozdsti_bot","id":"tg_name_hPBHYp_by_stickers_stealer_bot","net.maunium.telegram.pack":null,"stickers":[{"body":"🐈","url":"mxc://matrix.org/HjrzgsWTRcQhpuadCecVCmiO","info":{"w":512,"h":512,"size":10269276,"mimetype":"image/webp","thumbnail_url":"mxc://matrix.org/SwxUqiAIYiugVJyAbKtlwCsK","thumbnail_info":{"w":320,"h":320,"size":7346,"mimetype":"image/webp"}},"msgtype":"m.sticker","id":"mxc://matrix.org/HjrzgsWTRcQhpuadCecVCmiO","net.maunium.telegram.sticker":null},{"body":"🐈","url":"mxc://matrix.org/iyvGDXCOyYjFDcIwyRjMwDkl","info":{"w":512,"h":486,"size":3064976,"mimetype":"image/webp","thumbnail_url":"mxc://matrix.org/clZgDlAPxVtXKTUpMqJnmcwA","thumbnail_info":{"w":320,"h":304,"size":4884,"mimetype":"image/webp"}},"msgtype":"m.sticker","id":"mxc://matrix.org/iyvGDXCOyYjFDcIwyRjMwDkl","net.maunium.telegram.sticker":null},{"body":"🐈","url":"mxc://matrix.org/gsQhFPROgNhzYbpAmYRjVCCD","info":{"w":512,"h":512,"size":11625300,"mimetype":"image/webp","thumbnail_url":"mxc://matrix.org/xkIExiQZYHKTepBtkwGVKUOl","thumbnail_info":{"w":320,"h":320,"size":6684,"mimetype":"image/webp"}},"msgtype":"m.sticker","id":"mxc://matrix.org/gsQhFPROgNhzYbpAmYRjVCCD","net.maunium.telegram.sticker":null},{"body":"🐈","url":"mxc://matrix.org/AIKfiJQlkXaEeKNXgIwVjAZI","info":{"w":432,"h":512,"size":7314656,"mimetype":"image/webp","thumbnail_url":"mxc://matrix.org/hKZXaPLcTAXlYFdbMslBPVqe","thumbnail_info":{"w":270,"h":320,"size":6654,"mimetype":"image/webp"}},"msgtype":"m.sticker","id":"mxc://matrix.org/AIKfiJQlkXaEeKNXgIwVjAZI","net.maunium.telegram.sticker":null},{"body":"🐈","url":"mxc://matrix.org/KdCMDUPeOZMgGzqheXeTMLGQ","info":{"w":512,"h":512,"size":7138292,"mimetype":"image/webp","thumbnail_url":"mxc://matrix.org/lNPvlDaOLlYqsUxjJBjczwge","thumbnail_info":{"w":320,"h":320,"size":4398,"mimetype":"image/webp"}},"msgtype":"m.sticker","id":"mxc://matrix.org/KdCMDUPeOZMgGzqheXeTMLGQ","net.maunium.telegram.sticker":null},{"body":"🐈","url":"mxc://matrix.org/iXNNzkztwaJpJOqrzNKGySRV","info":{"w":512,"h":393,"size":5340892,"mimetype":"image/webp","thumbnail_url":"mxc://matrix.org/ttVeenmZFaxjEsKgEGDlOFJk","thumbnail_info":{"w":320,"h":246,"size":5162,"mimetype":"image/webp"}},"msgtype":"m.sticker","id":"mxc://matrix.org/iXNNzkztwaJpJOqrzNKGySRV","net.maunium.telegram.sticker":null},{"body":"🐈","url":"mxc://matrix.org/wTmqpUNvjRgoiEaSAfyJqfEs","info":{"w":512,"h":495,"size":6402156,"mimetype":"image/webp","thumbnail_url":"mxc://matrix.org/NhOAGtUkWyqXswfLMjQoKLfG","thumbnail_info":{"w":320,"h":309,"size":4420,"mimetype":"image/webp"}},"msgtype":"m.sticker","id":"mxc://matrix.org/wTmqpUNvjRgoiEaSAfyJqfEs","net.maunium.telegram.sticker":null},{"body":"🐈","url":"mxc://matrix.org/MFtyiqpvSuycdDDHnUBLpwWD","info":{"w":512,"h":416,"size":5015674,"mimetype":"image/webp","thumbnail_url":"mxc://matrix.org/FdZTSZnrKPxNSdVICgiNEwRX","thumbnail_info":{"w":320,"h":260,"size":5026,"mimetype":"image/webp"}},"msgtype":"m.sticker","id":"mxc://matrix.org/MFtyiqpvSuycdDDHnUBLpwWD","net.maunium.telegram.sticker":null},{"body":"🐈","url":"mxc://matrix.org/fwXZYcMiloNUWzyiLBEzJMcj","info":{"w":512,"h":512,"size":5804216,"mimetype":"image/webp","thumbnail_url":"mxc://matrix.org/esfhiOOkpkVRiwGDtjVcvomY","thumbnail_info":{"w":320,"h":320,"size":3086,"mimetype":"image/webp"}},"msgtype":"m.sticker","id":"mxc://matrix.org/fwXZYcMiloNUWzyiLBEzJMcj","net.maunium.telegram.sticker":null},{"body":"🐈","url":"mxc://matrix.org/hiyrCUrzjpfdtmPvqPbmBdNf","info":{"w":512,"h":186,"size":2292236,"mimetype":"image/webp","thumbnail_url":"mxc://matrix.org/uUJGuTiPQoXuzfbgnRJSgBhk","thumbnail_info":{"w":320,"h":116,"size":1746,"mimetype":"image/webp"}},"msgtype":"m.sticker","id":"mxc://matrix.org/hiyrCUrzjpfdtmPvqPbmBdNf","net.maunium.telegram.sticker":null},{"body":"🐈","url":"mxc://matrix.org/RTkHPGubrtlYIswZREeCQkFu","info":{"w":512,"h":512,"size":6896952,"mimetype":"image/webp","thumbnail_url":"mxc://matrix.org/pNlXgXdBoafcigurXLGhJsSq","thumbnail_info":{"w":320,"h":320,"size":11510,"mimetype":"image/webp"}},"msgtype":"m.sticker","id":"mxc://matrix.org/RTkHPGubrtlYIswZREeCQkFu","net.maunium.telegram.sticker":null},{"body":"🐈","url":"mxc://matrix.org/ghJAMKTJmJOUDiSfvcUtYrGu","info":{"w":512,"h":512,"size":9215506,"mimetype":"image/webp","thumbnail_url":"mxc://matrix.org/loiMyDxXiGpqOhxYXJZrvGfg","thumbnail_info":{"w":320,"h":320,"size":7298,"mimetype":"image/webp"}},"msgtype":"m.sticker","id":"mxc://matrix.org/ghJAMKTJmJOUDiSfvcUtYrGu","net.maunium.telegram.sticker":null},{"body":"🐈","url":"mxc://matrix.org/SSVJxmsGyBozZXNBtcYzgJER","info":{"w":512,"h":450,"size":6996762,"mimetype":"image/webp","thumbnail_url":"mxc://matrix.org/KzsxfKrEUowCpMSuGniSDehD","thumbnail_info":{"w":320,"h":281,"size":6856,"mimetype":"image/webp"}},"msgtype":"m.sticker","id":"mxc://matrix.org/SSVJxmsGyBozZXNBtcYzgJER","net.maunium.telegram.sticker":null},{"body":"🐈","url":"mxc://matrix.org/MUcpvvUpYPDHZHPyroDTrvFh","info":{"w":512,"h":506,"size":3101006,"mimetype":"image/webp","thumbnail_url":"mxc://matrix.org/maSnqutFaLuznMggYJqzqwmb","thumbnail_info":{"w":320,"h":316,"size":4716,"mimetype":"image/webp"}},"msgtype":"m.sticker","id":"mxc://matrix.org/MUcpvvUpYPDHZHPyroDTrvFh","net.maunium.telegram.sticker":null},{"body":"🐈","url":"mxc://matrix.org/hCeLBREpSWEuLjmNTZafwmho","info":{"w":512,"h":512,"size":12499062,"mimetype":"image/webp","thumbnail_url":"mxc://matrix.org/bpEJwdkxaYxiXkXRqxCUryqH","thumbnail_info":{"w":320,"h":320,"size":10686,"mimetype":"image/webp"}},"msgtype":"m.sticker","id":"mxc://matrix.org/hCeLBREpSWEuLjmNTZafwmho","net.maunium.telegram.sticker":null},{"body":"🐈","url":"mxc://matrix.org/zJGwbqNkyQhSMWnYYpLbVTMH","info":{"w":376,"h":512,"size":7661866,"mimetype":"image/webp","thumbnail_url":"mxc://matrix.org/IyChIZRGDvPDXGQrofzMlvha","thumbnail_info":{"w":235,"h":320,"size":8966,"mimetype":"image/webp"}},"msgtype":"m.sticker","id":"mxc://matrix.org/zJGwbqNkyQhSMWnYYpLbVTMH","net.maunium.telegram.sticker":null},{"body":"🐈","url":"mxc://matrix.org/AnbhXHaSWiLwUeMANOVotUXt","info":{"w":512,"h":512,"size":10183466,"mimetype":"image/webp","thumbnail_url":"mxc://matrix.org/tzDpWkVXQsdcstcCAsDLNgdM","thumbnail_info":{"w":320,"h":320,"size":4192,"mimetype":"image/webp"}},"msgtype":"m.sticker","id":"mxc://matrix.org/AnbhXHaSWiLwUeMANOVotUXt","net.maunium.telegram.sticker":null},{"body":"🐈","url":"mxc://matrix.org/lYOwXRucfamKrcZPEWHAfvUA","info":{"w":512,"h":385,"size":7861280,"mimetype":"image/webp","thumbnail_url":"mxc://matrix.org/RvwZUgNpTgeBmmyCdwURQoaD","thumbnail_info":{"w":320,"h":241,"size":3008,"mimetype":"image/webp"}},"msgtype":"m.sticker","id":"mxc://matrix.org/lYOwXRucfamKrcZPEWHAfvUA","net.maunium.telegram.sticker":null},{"body":"🐈","url":"mxc://matrix.org/ippUKyWPKUnnANYLqkBTSeSq","info":{"w":512,"h":375,"size":6740862,"mimetype":"image/webp","thumbnail_url":"mxc://matrix.org/iljKcavpeWFpVoKbuxsAkHXm","thumbnail_info":{"w":320,"h":234,"size":3898,"mimetype":"image/webp"}},"msgtype":"m.sticker","id":"mxc://matrix.org/ippUKyWPKUnnANYLqkBTSeSq","net.maunium.telegram.sticker":null},{"body":"🐈","url":"mxc://matrix.org/ULwkedYGFlonXmKVGnyrVxbT","info":{"w":512,"h":512,"size":10910720,"mimetype":"image/webp","thumbnail_url":"mxc://matrix.org/RefpaWlEySJxQNuJpOXyGWTF","thumbnail_info":{"w":320,"h":320,"size":6346,"mimetype":"image/webp"}},"msgtype":"m.sticker","id":"mxc://matrix.org/ULwkedYGFlonXmKVGnyrVxbT","net.maunium.telegram.sticker":null},{"body":"🐈","url":"mxc://matrix.org/AHCNNzdZGacTojrEBmwEJtWw","info":{"w":512,"h":512,"size":9720428,"mimetype":"image/webp","thumbnail_url":"mxc://matrix.org/pubeHapvGvTMGIjHLsViHTzH","thumbnail_info":{"w":320,"h":320,"size":9812,"mimetype":"image/webp"}},"msgtype":"m.sticker","id":"mxc://matrix.org/AHCNNzdZGacTojrEBmwEJtWw","net.maunium.telegram.sticker":null},{"body":"🐈","url":"mxc://matrix.org/FbvnaJNMpNykNoSUjSQymZll","info":{"w":512,"h":287,"size":6163096,"mimetype":"image/webp","thumbnail_url":"mxc://matrix.org/lmZhhrmZDmHRIlVYmYvNqlyc","thumbnail_info":{"w":320,"h":179,"size":6094,"mimetype":"image/webp"}},"msgtype":"m.sticker","id":"mxc://matrix.org/FbvnaJNMpNykNoSUjSQymZll","net.maunium.telegram.sticker":null},{"body":"🐈","url":"mxc://matrix.org/qyCPEkZQGxeqdEeEbyUOnYzs","info":{"w":512,"h":284,"size":6195254,"mimetype":"image/webp","thumbnail_url":"mxc://matrix.org/NGIasIlkJAiYxMmDaNimvpTw","thumbnail_info":{"w":320,"h":177,"size":8726,"mimetype":"image/webp"}},"msgtype":"m.sticker","id":"mxc://matrix.org/qyCPEkZQGxeqdEeEbyUOnYzs","net.maunium.telegram.sticker":null},{"body":"🐈","url":"mxc://matrix.org/lrSIqDPxZpQazkytolNwNvEi","info":{"w":512,"h":512,"size":3609338,"mimetype":"image/webp","thumbnail_url":"mxc://matrix.org/KuWDfBwggZLQiNXjWvcEzHWc","thumbnail_info":{"w":320,"h":320,"size":6962,"mimetype":"image/webp"}},"msgtype":"m.sticker","id":"mxc://matrix.org/lrSIqDPxZpQazkytolNwNvEi","net.maunium.telegram.sticker":null},{"body":"🐈","url":"mxc://matrix.org/EIPMPAWkDBYtOaEpzVuBTLlu","info":{"w":512,"h":512,"size":6001676,"mimetype":"image/webp","thumbnail_url":"mxc://matrix.org/LsynrMVZPynPezETrMmTvTbV","thumbnail_info":{"w":320,"h":320,"size":3950,"mimetype":"image/webp"}},"msgtype":"m.sticker","id":"mxc://matrix.org/EIPMPAWkDBYtOaEpzVuBTLlu","net.maunium.telegram.sticker":null},{"body":"🐈","url":"mxc://matrix.org/niFZBhPziHvfocaOxvbZwcEq","info":{"w":456,"h":512,"size":10718712,"mimetype":"image/webp","thumbnail_url":"mxc://matrix.org/zuxgFihMkAcaHtZrNtWRatMx","thumbnail_info":{"w":285,"h":320,"size":5126,"mimetype":"image/webp"}},"msgtype":"m.sticker","id":"mxc://matrix.org/niFZBhPziHvfocaOxvbZwcEq","net.maunium.telegram.sticker":null},{"body":"🐈","url":"mxc://matrix.org/manyVapawVbeNRIHBKIKIncf","info":{"w":512,"h":264,"size":4990846,"mimetype":"image/webp","thumbnail_url":"mxc://matrix.org/ORoVuYnDQcVBQUhMwTiGVRqw","thumbnail_info":{"w":320,"h":165,"size":2966,"mimetype":"image/webp"}},"msgtype":"m.sticker","id":"mxc://matrix.org/manyVapawVbeNRIHBKIKIncf","net.maunium.telegram.sticker":null},{"body":"🐈","url":"mxc://matrix.org/DrVUNsKVvKLaYnBEiDVWpznW","info":{"w":512,"h":427,"size":6126730,"mimetype":"image/webp","thumbnail_url":"mxc://matrix.org/xxwAgtqugYJlLKUnAKOikUYU","thumbnail_info":{"w":320,"h":267,"size":4950,"mimetype":"image/webp"}},"msgtype":"m.sticker","id":"mxc://matrix.org/DrVUNsKVvKLaYnBEiDVWpznW","net.maunium.telegram.sticker":null},{"body":"🐈","url":"mxc://matrix.org/BBHDIwPyEktMUZkuLzyHaXlx","info":{"w":512,"h":366,"size":7380030,"mimetype":"image/webp","thumbnail_url":"mxc://matrix.org/qSMSuUjFZXEWBOUgjKdnNcij","thumbnail_info":{"w":320,"h":229,"size":4322,"mimetype":"image/webp"}},"msgtype":"m.sticker","id":"mxc://matrix.org/BBHDIwPyEktMUZkuLzyHaXlx","net.maunium.telegram.sticker":null},{"body":"🐈","url":"mxc://matrix.org/NpjivWNVvtRLhrDJmoDcvCaD","info":{"w":512,"h":512,"size":19790258,"mimetype":"image/webp","thumbnail_url":"mxc://matrix.org/ssuJrVAAATIowGnRcZmMEpfi","thumbnail_info":{"w":320,"h":320,"size":7758,"mimetype":"image/webp"}},"msgtype":"m.sticker","id":"mxc://matrix.org/NpjivWNVvtRLhrDJmoDcvCaD","net.maunium.telegram.sticker":null}]}